OSM2LES/__init__.py
OSM2LES/__main__.py
OSM2LES/entropy.py
OSM2LES/evalgeo.py
OSM2LES/extract.py
OSM2LES/rasterization.py
OSM2LES/results.py
OSM2LES/settings.py
OSM2LES/topo.py
OSM2LES-0.0.18.dist-info/METADATA
OSM2LES-0.0.18.dist-info/WHEEL
OSM2LES-0.0.18.dist-info/top_level.txt
OSM2LES-0.0.18.dist-info/RECORD
